{
  "user": [
    {
      "id": "853b",
      "email": "890",
      "password": "890",
      "userName": "890"
    },
    {
      "id": "1852",
      "email": "1234",
      "password": "1234",
      "userName": "1234"
    },
    {
      "id": "35f5",
      "email": "234",
      "password": "234",
      "userName": "234"
    },
    {
      "id": "3495",
      "email": "567",
      "password": "567",
      "userName": "567"
    },
    {
      "id": "d685",
      "email": "678",
      "password": "678",
      "userName": "678"
    },
    {
      "id": "a096",
      "email": "1234",
      "password": "1234"
    },
    {
      "id": "2f65",
      "email": "1234",
      "password": "1234"
    },
    {
      "id": "6233",
      "email": "1234",
      "password": "1234"
    },
    {
      "id": "653d",
      "email": "1234",
      "password": "1234"
    },
    {
      "id": "5115",
      "email": "1234",
      "password": "1234"
    },
    {
      "id": "ccb8",
      "email": "1234",
      "password": "1234"
    },
    {
      "id": "8027",
      "email": "1234",
      "password": "1234"
    },
    {
      "id": "786a",
      "email": "1234",
      "password": "1234"
    },
    {
      "id": "d506",
      "email": "1234",
      "password": "1234"
    },
    {
      "id": "506c",
      "email": "1234",
      "password": "1234"
    },
    {
      "id": "5450",
      "email": "1234",
      "password": "1234"
    },
    {
      "id": "f775",
      "email": "1234",
      "password": "1234"
    },
    {
      "id": "d939",
      "email": "1234",
      "password": "1234"
    },
    {
      "id": "8eb5",
      "email": "1234",
      "password": "1234"
    },
    {
      "id": "d747",
      "email": "1234",
      "password": "1234"
    },
    {
      "id": "f83a",
      "email": "1234",
      "password": "1234"
    },
    {
      "id": "4a30",
      "email": "1234",
      "password": "1234"
    },
    {
      "id": "1b5d",
      "email": "1234",
      "password": "1234"
    },
    {
      "id": "df8f",
      "email": "1234",
      "password": "1234"
    },
    {
      "id": "e0aa",
      "email": "1234",
      "password": "1234"
    },
    {
      "id": "c5bb",
      "email": "1234",
      "password": "1234"
    },
    {
      "id": "9938"
    },
    {
      "id": "1b40",
      "email": "1234",
      "password": "1234"
    },
    {
      "id": "360d",
      "email": "1234",
      "password": "1234"
    },
    {
      "id": "fc71",
      "email": "1234",
      "password": "1234"
    },
    {
      "id": "37dc",
      "email": "1234",
      "password": "1234"
    },
    {
      "id": "8366",
      "email": "1234",
      "password": "1234"
    },
    {
      "id": "7f5a",
      "email": "1234",
      "password": "1234"
    },
    {
      "id": "888a",
      "email": "1234",
      "password": "1234"
    },
    {
      "id": "226c",
      "email": "1234",
      "password": "1234"
    },
    {
      "id": "ffc0",
      "email": "1234",
      "password": "1234"
    },
    {
      "id": "5f47",
      "email": "1234",
      "password": "1234"
    },
    {
      "id": "1bba",
      "email": "1234",
      "password": "1234"
    },
    {
      "id": "45a7",
      "email": "1234",
      "password": "1234"
    },
    {
      "id": "1259",
      "email": "1234",
      "password": "1234"
    },
    {
      "id": "d0f3",
      "email": "1234",
      "password": "1234"
    },
    {
      "id": "ef88",
      "email": "1234",
      "password": "1234"
    },
    {
      "id": "a29f",
      "email": "1234",
      "password": "1234"
    },
    {
      "id": "9391",
      "email": "1234",
      "password": "1234"
    },
    {
      "id": "92de",
      "email": "1234",
      "password": "1234"
    },
    {
      "id": "0acb",
      "email": "1234",
      "password": "1234"
    },
    {
      "id": "4229",
      "email": "1234",
      "password": "1234"
    },
    {
      "id": "b1be",
      "email": "1234",
      "password": "1234"
    },
    {
      "id": "2963",
      "email": "1234",
      "password": "1234"
    },
    {
      "id": "4419",
      "email": "1234",
      "password": "1234"
    },
    {
      "id": "29ab",
      "email": "1234",
      "password": "1234"
    },
    {
      "id": "d3d9",
      "email": "1234",
      "password": "1234"
    },
    {
      "id": "8e4e",
      "email": "1234",
      "password": "1234"
    },
    {
      "id": "13d0",
      "email": "1234",
      "password": "1234"
    },
    {
      "id": "e0cd",
      "email": "1234",
      "password": "1234"
    },
    {
      "id": "061e",
      "email": "1234",
      "password": "1234"
    },
    {
      "id": "28e5",
      "email": "1234",
      "password": "1234"
    },
    {
      "id": "b070",
      "email": "1234",
      "password": "1234"
    },
    {
      "id": "50b9",
      "email": "1234",
      "password": "1234"
    },
    {
      "id": "d99e",
      "email": "1234",
      "password": "1234"
    },
    {
      "id": "6d0b",
      "email": "1234",
      "password": "1234"
    },
    {
      "id": "7ec5",
      "email": "1234",
      "password": "1234"
    },
    {
      "id": "0ff3",
      "email": "1234",
      "password": "1234"
    },
    {
      "id": "6610",
      "email": "1234",
      "password": "1234"
    },
    {
      "id": "f54a",
      "email": "1234",
      "password": "1234"
    },
    {
      "id": "6d11",
      "email": "1234",
      "password": "1234"
    },
    {
      "id": "030c",
      "email": "1234",
      "password": "1234"
    },
    {
      "id": "faa8",
      "email": "1234",
      "password": "1234"
    },
    {
      "id": "dec1",
      "email": "1234",
      "password": "1234"
    },
    {
      "id": "5093",
      "email": "1234",
      "password": "1234"
    },
    {
      "id": "0429",
      "email": "1234",
      "password": "1234"
    },
    {
      "id": "1395",
      "email": "1234",
      "password": "1234"
    },
    {
      "id": "44f4",
      "email": "1234",
      "password": "1234"
    },
    {
      "id": "266d",
      "email": "1234",
      "password": "1234"
    },
    {
      "id": "c3af",
      "email": "1234",
      "password": "1234"
    },
    {
      "id": "ee78",
      "email": "1234",
      "password": "1234"
    },
    {
      "id": "2ced",
      "email": "1234",
      "password": "1234"
    },
    {
      "id": "b238",
      "email": "1234",
      "password": "1234"
    },
    {
      "id": "b652",
      "email": "1234",
      "password": "1234"
    },
    {
      "id": "c1fc",
      "email": "1234",
      "password": "1234"
    },
    {
      "id": "526a",
      "email": "1234",
      "password": "1234"
    },
    {
      "id": "e0bc",
      "email": "1234",
      "password": "1234"
    },
    {
      "id": "92c8",
      "email": "1234",
      "password": "1234"
    },
    {
      "id": "4e36",
      "email": "1234",
      "password": "1234"
    },
    {
      "id": "794c",
      "email": "1234",
      "password": "1234"
    },
    {
      "id": "fbbe",
      "email": "1234",
      "password": "1234"
    },
    {
      "id": "d9bc",
      "email": "1234",
      "password": "1234"
    },
    {
      "id": "018d",
      "email": "1234",
      "password": "1234"
    },
    {
      "id": "e556",
      "email": "1234",
      "password": "1234"
    },
    {
      "id": "8b9e",
      "email": "1234",
      "password": "1234"
    },
    {
      "id": "6d5c",
      "email": "1234",
      "password": "1234"
    },
    {
      "id": "030b",
      "email": "1234",
      "password": "1234"
    },
    {
      "id": "4b34",
      "email": "1234",
      "password": "1234"
    },
    {
      "id": "89d3",
      "email": "1234",
      "password": "1234"
    },
    {
      "id": "9e92",
      "email": "1234",
      "password": "1234"
    },
    {
      "id": "2db3",
      "email": "1234",
      "password": "1234"
    },
    {
      "id": "e56b",
      "email": "1234",
      "password": "1234"
    },
    {
      "id": "2179",
      "email": "1234",
      "password": "1234"
    },
    {
      "id": "c657",
      "email": "1234",
      "password": "1234"
    },
    {
      "id": "3dd9",
      "email": "1234",
      "password": "1234"
    },
    {
      "id": "2329",
      "email": "1234",
      "password": "1234"
    },
    {
      "id": "d760",
      "email": "1234",
      "password": "1234"
    },
    {
      "id": "c05d",
      "email": "1234",
      "password": "1234"
    },
    {
      "id": "1be3",
      "email": "1234",
      "password": "1234"
    },
    {
      "id": "3e78",
      "email": "1234",
      "password": "1234"
    },
    {
      "id": "2f66",
      "email": "1234",
      "password": "1234"
    },
    {
      "id": "dc41",
      "email": "1234",
      "password": "1234"
    },
    {
      "id": "0cb8",
      "email": "1234",
      "password": "1234"
    },
    {
      "id": "c96e",
      "email": "1234",
      "password": "1234"
    },
    {
      "id": "12ba",
      "email": "1234",
      "password": "1234"
    },
    {
      "id": "7e0c",
      "email": "1234",
      "password": "1234"
    }
  ],
  "moviePost": [
    {
      "idx": 1,
      "date": "2024-01-10",
      "starRating": 5,
      "movie": {
        "id": 8392,
        "poster_path": "/c9zCkL0rTkNQ1HB9cmeFIqbkS50.jpg",
        "title": "이웃집 토토로",
        "release_date": "1988-04-16"
      },
      "movieReview": "토토로는 귀여워\n\n영화는 재미있어 \n\n또 보고 싶어",
      "userEmail": "1234",
      "id": "83d9"
    },
    {
      "idx": 2,
      "date": "2024-01-11",
      "starRating": 4,
      "movie": {
        "id": 508883,
        "poster_path": "/kmoScy628A6JWv8mmd2ofrYv16T.jpg",
        "title": "그대들은 어떻게 살 것인가",
        "release_date": "2023-07-14"
      },
      "movieReview": "우와 진짜 무서운 영화야 \n\n하지만 정말 재미있었고, 또 보고 싶어",
      "userEmail": "1234",
      "id": "5c2e"
    },
    {
      "idx": 3,
      "date": "2024-01-03",
      "starRating": 4,
      "movie": {
        "id": 12429,
        "poster_path": "/tGSuFBsqdXxIz3fTSBfsZU9FBMN.jpg",
        "title": "벼랑 위의 포뇨",
        "release_date": "2008-07-19"
      },
      "movieReview": "지브리하면 역시 포뇨지",
      "userEmail": "1234",
      "id": "f42a"
    },
    {
      "idx": 4,
      "date": "2024-01-12",
      "starRating": 2,
      "movie": {
        "id": 16859,
        "poster_path": "/yEbyzK1cLDoZVIJV6auSr9yN5fG.jpg",
        "title": "마녀 배달부 키키",
        "release_date": "1989-07-29"
      },
      "movieReview": "키키는 진짜 재미있어",
      "userEmail": "1234",
      "id": "db6a"
    },
    {
      "idx": 5,
      "date": "2024-01-04",
      "starRating": 1,
      "movie": {
        "id": 129,
        "poster_path": "/aZuBfbR0PnCb2up7lqHDsgJlLjs.jpg",
        "title": "센과 치히로의 행방불명",
        "release_date": "2001-07-20"
      },
      "movieReview": "이건 좀  별로였다 ;; ㅋㅋㅋ 그치",
      "userEmail": "1234",
      "id": "5240"
    },
    {
      "idx": 6,
      "date": "2024-01-10",
      "starRating": 3,
      "movie": {
        "id": 51739,
        "poster_path": "/1Xz0WSXeXzyTCbHADGBpmEaDpZl.jpg",
        "title": "마루 밑 아리에티",
        "release_date": "2010-07-16"
      },
      "movieReview": "마루 밑 에리아티 ~",
      "userEmail": "1234",
      "id": "3fae"
    },
    {
      "idx": 7,
      "date": "2024-01-04",
      "starRating": 3,
      "movie": {
        "id": 596302,
        "poster_path": "/5xHucNDRIxNKYCOl8zWWDrL5dBe.jpg",
        "title": "짱구는 못말려 극장판: 신혼여행 허리케인~ 사라진 아빠!",
        "release_date": "2019-04-19"
      },
      "movieReview": "짱구야짱구야\n짱구야\n\n짱구야\n짱구야\n짱구야\n",
      "userEmail": "1234",
      "id": "4104"
    },
    {
      "idx": 8,
      "date": "2024-01-04",
      "starRating": 5,
      "movie": {
        "id": 673,
        "poster_path": "/anwNl1xbzXoj5Ax1nVw3WoDzHlw.jpg",
        "title": "해리 포터와 아즈카반의 죄수",
        "release_date": "2004-05-31"
      },
      "movieReview": "해리포터와 아즈카반의 죄수 재밌어\n\n내가 옛날부터 좋아하던 영화야",
      "userEmail": "1234",
      "id": "666e"
    },
    {
      "idx": 9,
      "date": "2024-01-10",
      "starRating": 2,
      "movie": {
        "id": 453575,
        "poster_path": "/rqJtClna9UjgTBAWBGZ2UzuEdye.jpg",
        "title": "짱구는 못말려 극장판: 습격!! 외계인 덩덩이",
        "release_date": "2017-04-15"
      },
      "movieReview": "외계인 짱구는 재미있어",
      "userEmail": "1234",
      "id": "e416"
    },
    {
      "idx": 10,
      "date": "2024-01-18",
      "starRating": 3,
      "movie": {
        "id": 109526,
        "poster_path": "/9djKSjGogao0ROefsa2YTeNy2w3.jpg",
        "title": "짱구는 못말려 극장판: 부리부리 왕국의 보물",
        "release_date": "1994-04-23"
      },
      "movieReview": "짱구야\n재밌다",
      "userEmail": "1234",
      "id": "0e7d"
    }
  ]
}